article_scrapper/__init__.py
article_scrapper/pipeline.py
article_scrapper/py.typed
article_scrapper/scrapper.py
article_scrapper/search.py
article_scrapper-0.1.0.dist-info/METADATA
article_scrapper-0.1.0.dist-info/WHEEL
article_scrapper-0.1.0.dist-info/licenses/LICENSE
article_scrapper-0.1.0.dist-info/RECORD
