Metadata-Version: 2.4
Name: article_scrapper
Version: 0.1.0
Summary: A simple library to scrape articles from the web using newspaper3k and search with DuckDuckGo
Project-URL: Homepage, https://github.com/yourusername/article_scrapper
Project-URL: Repository, https://github.com/yourusername/article_scrapper
Project-URL: Issues, https://github.com/yourusername/article_scrapper/issues
Author-email: Your Name <your.email@example.com>
License: MIT
License-File: LICENSE
Keywords: article,duckduckgo,news,newspaper,scraper,web-scraping
Classifier: Development Status :: 4 - Beta
Classifier: Intended Audience :: Developers
Classifier: License :: OSI Approved :: MIT License
Classifier: Operating System :: OS Independent
Classifier: Programming Language :: Python :: 3
Classifier: Programming Language :: Python :: 3.10
Classifier: Programming Language :: Python :: 3.11
Classifier: Programming Language :: Python :: 3.12
Classifier: Topic :: Internet :: WWW/HTTP
Classifier: Topic :: Text Processing
Requires-Python: >=3.10
Requires-Dist: ddgs>=9.9.3
Requires-Dist: lxml-html-clean>=0.4.3
Requires-Dist: newspaper3k>=0.2.8
